jomiel_comm/__init__.py
jomiel_comm/formatter.py
jomiel_comm/inquiry.py
jomiel_comm/auth/__init__.py
jomiel_comm/auth/curve.py
jomiel_comm/auth/ssh.py
jomiel_comm-0.1.0.dist-info/LICENSE
jomiel_comm-0.1.0.dist-info/METADATA
jomiel_comm-0.1.0.dist-info/NOTICE
jomiel_comm-0.1.0.dist-info/WHEEL
jomiel_comm-0.1.0.dist-info/top_level.txt
jomiel_comm-0.1.0.dist-info/zip-safe
jomiel_comm-0.1.0.dist-info/RECORD
