Metadata-Version: 2.1
Name: jomiel-comm
Version: 0.1.0
Summary: Python library for communicating with jomiel
Home-page: https://github.com/guendto/jomiel-comm
Author: Toni Gündoğdu
Author-email: 47444442+guendto@users.noreply.github.com
License: Apache2.0
Platform: any
Classifier: Development Status :: 4 - Beta
Classifier: License :: OSI Approved :: Apache Software License
Classifier: Programming Language :: Python :: 3.6
Classifier: Programming Language :: Python :: 3.7
Classifier: Programming Language :: Python :: 3.8
Requires-Python: >=3.6
Requires-Dist: jomiel-messages
Requires-Dist: pyzmq
Requires-Dist: ruamel.yaml
Requires-Dist: ujson
